shapeandshare/light/__init__.py
shapeandshare/light/const.py
shapeandshare/light/display.py
shapeandshare/light/loop.py
shapeandshare/light/main.py
shapeandshare/light/assets/__init__.py
shapeandshare/light/assets/tiles/__init__.py
shapeandshare/light/assets/tiles/dirt.png
shapeandshare/light/assets/tiles/forest.png
shapeandshare/light/assets/tiles/grass.png
shapeandshare/light/assets/tiles/ocean.png
shapeandshare/light/assets/tiles/rock.png
shapeandshare/light/assets/tiles/shore.png
shapeandshare/light/assets/tiles/unknown.png
shapeandshare/light/assets/tiles/water.png
shapeandshare/light/contracts/__init__.py
shapeandshare/light/contracts/dtos/__init__.py
shapeandshare/light/contracts/dtos/center_dim.py
shapeandshare/light/contracts/dtos/center_metadata.py
shapeandshare/light/contracts/sprites/__init__.py
shapeandshare/light/contracts/sprites/chunk.py
shapeandshare/light/contracts/sprites/tile.py
shapeandshare.light-0.5.3.dist-info/LICENSE
shapeandshare.light-0.5.3.dist-info/METADATA
shapeandshare.light-0.5.3.dist-info/WHEEL
shapeandshare.light-0.5.3.dist-info/entry_points.txt
shapeandshare.light-0.5.3.dist-info/top_level.txt
shapeandshare.light-0.5.3.dist-info/RECORD
