Metadata-Version: 2.1
Name: shapeandshare.light
Version: 0.5.3
Summary: The Light
Author-email: "Joshua C. Burt" <joshburt@shapeandshare.com>
License: MIT License
Project-URL: Homepage, https://github.com/shapeandshare/light
Project-URL: Issues, https://github.com/shapeandshare/light/issues
Classifier: Programming Language :: Python :: 3
Classifier: License :: OSI Approved :: MIT License
Classifier: Operating System :: OS Independent
Requires-Python: >=3.12
License-File: LICENSE
Requires-Dist: pydantic
Requires-Dist: pygame
Requires-Dist: shapeandshare.darkness
Requires-Dist: click
